dpdata/__about__.py
dpdata/__init__.py
dpdata/__main__.py
dpdata/_version.py
dpdata/ase_calculator.py
dpdata/bond_order_system.py
dpdata/cli.py
dpdata/data_type.py
dpdata/driver.py
dpdata/format.py
dpdata/periodic_table.json
dpdata/periodic_table.py
dpdata/plugin.py
dpdata/py.typed
dpdata/stat.py
dpdata/system.py
dpdata/unit.py
dpdata/utils.py
dpdata/abacus/__init__.py
dpdata/abacus/md.py
dpdata/abacus/relax.py
dpdata/abacus/scf.py
dpdata/abacus/stru.py
dpdata/amber/__init__.py
dpdata/amber/mask.py
dpdata/amber/md.py
dpdata/amber/sqm.py
dpdata/cp2k/__init__.py
dpdata/cp2k/cell.py
dpdata/cp2k/output.py
dpdata/deepmd/__init__.py
dpdata/deepmd/comp.py
dpdata/deepmd/hdf5.py
dpdata/deepmd/mixed.py
dpdata/deepmd/raw.py
dpdata/dftbplus/__init__.py
dpdata/dftbplus/output.py
dpdata/fhi_aims/__init__.py
dpdata/fhi_aims/output.py
dpdata/gaussian/__init__.py
dpdata/gaussian/fchk.py
dpdata/gaussian/gjf.py
dpdata/gaussian/log.py
dpdata/gromacs/__init__.py
dpdata/gromacs/gro.py
dpdata/lammps/__init__.py
dpdata/lammps/dump.py
dpdata/lammps/lmp.py
dpdata/md/__init__.py
dpdata/md/msd.py
dpdata/md/pbc.py
dpdata/md/rdf.py
dpdata/md/water.py
dpdata/openmx/__init__.py
dpdata/openmx/omx.py
dpdata/orca/__init__.py
dpdata/orca/output.py
dpdata/plugins/3dmol.py
dpdata/plugins/__init__.py
dpdata/plugins/abacus.py
dpdata/plugins/amber.py
dpdata/plugins/ase.py
dpdata/plugins/cp2k.py
dpdata/plugins/deepmd.py
dpdata/plugins/dftbplus.py
dpdata/plugins/fhi_aims.py
dpdata/plugins/gaussian.py
dpdata/plugins/gromacs.py
dpdata/plugins/lammps.py
dpdata/plugins/list.py
dpdata/plugins/n2p2.py
dpdata/plugins/openmx.py
dpdata/plugins/orca.py
dpdata/plugins/psi4.py
dpdata/plugins/pwmat.py
dpdata/plugins/pymatgen.py
dpdata/plugins/qe.py
dpdata/plugins/rdkit.py
dpdata/plugins/siesta.py
dpdata/plugins/vasp.py
dpdata/plugins/xyz.py
dpdata/psi4/__init__.py
dpdata/psi4/input.py
dpdata/psi4/output.py
dpdata/pwmat/__init__.py
dpdata/pwmat/atomconfig.py
dpdata/pwmat/movement.py
dpdata/pymatgen/__init__.py
dpdata-1.0.0.dist-info/licenses/LICENSE
dpdata-1.0.0.dist-info/METADATA
dpdata-1.0.0.dist-info/WHEEL
dpdata-1.0.0.dist-info/entry_points.txt
dpdata-1.0.0.dist-info/top_level.txt
dpdata-1.0.0.dist-info/RECORD
