Metadata-Version: 2.4
Name: dpdata
Version: 1.0.0
Summary: Manipulating data formats of DeePMD-kit, VASP, QE, PWmat, and LAMMPS, etc.
Author: DeepModeling
Author-email: Han Wang <wang_han@iapcm.ac.cn>
License:                    GNU LESSER GENERAL PUBLIC LICENSE
Project-URL: Homepage, https://github.com/deepmodeling/dpdata
Project-URL: documentation, https://docs.deepmodeling.com/projects/dpdata
Project-URL: repository, https://github.com/deepmodeling/dpdata
Keywords: lammps,vasp,deepmd-kit
Classifier: Programming Language :: Python :: 3.8
Classifier: Programming Language :: Python :: 3.9
Classifier: Programming Language :: Python :: 3.10
Classifier: Programming Language :: Python :: 3.11
Classifier: License :: OSI Approved :: GNU Lesser General Public License v3 (LGPLv3)
Requires-Python: >=3.8
License-File: LICENSE
Requires-Dist: numpy>=1.14.3
Requires-Dist: monty
Requires-Dist: scipy
Requires-Dist: h5py
Requires-Dist: wcmatch
Requires-Dist: importlib_metadata>=1.4; python_version < "3.8"
Requires-Dist: typing_extensions; python_version < "3.8"
Provides-Extra: test
Provides-Extra: ase
Requires-Dist: ase; extra == "ase"
Provides-Extra: amber
Requires-Dist: parmed; python_version >= "3.8" and extra == "amber"
Requires-Dist: parmed<4; python_version < "3.8" and extra == "amber"
Provides-Extra: pymatgen
Requires-Dist: pymatgen; extra == "pymatgen"
Provides-Extra: docs
Requires-Dist: sphinx; extra == "docs"
Requires-Dist: recommonmark; extra == "docs"
Requires-Dist: sphinx-book-theme; extra == "docs"
Requires-Dist: numpydoc; extra == "docs"
Requires-Dist: myst-parser; extra == "docs"
Requires-Dist: deepmodeling-sphinx>=0.3.0; extra == "docs"
Requires-Dist: sphinx-argparse<0.5.0; extra == "docs"
Requires-Dist: rdkit; extra == "docs"
Requires-Dist: jupyterlite-sphinx; extra == "docs"
Requires-Dist: jupyterlite-xeus; extra == "docs"
Provides-Extra: benchmark
Requires-Dist: pytest; extra == "benchmark"
Requires-Dist: pytest-codspeed; extra == "benchmark"
Dynamic: license-file
